poetry_exp/__init__.py
poetry_exp/flask_app.py
poetry_exp/mypy/Dockerfile
poetry_exp/mypy/__init__.py
poetry_exp/mypy/app/Iterator_generator/custom_iterator.py
poetry_exp/mypy/app/Iterator_generator/gen.py
poetry_exp/mypy/app/Iterator_generator/genaratorDemo.py
poetry_exp/mypy/app/Iterator_generator/yieldDemo.py
poetry_exp/mypy/app/README.md
poetry_exp/mypy/app/__init__.py
poetry_exp/mypy/app/ansible_exp/call_playbook.py
poetry_exp/mypy/app/ansible_exp/call_playbook2.py
poetry_exp/mypy/app/ansible_exp/call_playbook3.py
poetry_exp/mypy/app/ansible_exp/call_playbook_and_get_result.py
poetry_exp/mypy/app/ansible_exp/call_playbook_and_get_result2.py
poetry_exp/mypy/app/ansible_exp/connect_vceter.py
poetry_exp/mypy/app/ansible_exp/get_datastores.yml
poetry_exp/mypy/app/ansible_exp/get_ds_info.yml
poetry_exp/mypy/app/ansible_exp/get_ds_selected_properties.yml
poetry_exp/mypy/app/ansible_exp/get_folder_info.yml
poetry_exp/mypy/app/ansible_exp/get_res_pool.yml
poetry_exp/mypy/app/ansible_exp/get_vm_info.yml
poetry_exp/mypy/app/ansible_exp/get_vm_info_by_name.yml
poetry_exp/mypy/app/ansible_exp/get_vm_info_by_vm_name_ouput.yml
poetry_exp/mypy/app/ansible_exp/get_vm_info_output.yml
poetry_exp/mypy/app/ansible_exp/get_vms.yml
poetry_exp/mypy/app/ansible_exp/get_vms2.yml
poetry_exp/mypy/app/ansible_exp/get_vms_selected_props.yml
poetry_exp/mypy/app/ansible_exp/plugin.vmware.yml
poetry_exp/mypy/app/ansible_exp/test_google.yml
poetry_exp/mypy/app/ansible_exp/vmware_vm_inventory.py
poetry_exp/mypy/app/ansible_exp/vmware_vm_inventory_plugin_info
poetry_exp/mypy/app/asyncio_exp/async_wait_exp.py
poetry_exp/mypy/app/asyncio_exp/asyncio_VS_Parallelism_VS_Concurrency
poetry_exp/mypy/app/asyncio_exp/asyncio_exp.py
poetry_exp/mypy/app/asyncio_exp/asyncio_exp2.py
poetry_exp/mypy/app/asyncio_exp/asyncio_exp3.py
poetry_exp/mypy/app/asyncio_exp/asyncio_first_exp.py
poetry_exp/mypy/app/asyncio_exp/asyncio_gather_exp_.py
poetry_exp/mypy/app/asyncio_exp/asyncio_http_exp.py
poetry_exp-0.1.1.dist-info/METADATA
poetry_exp-0.1.1.dist-info/WHEEL
poetry_exp-0.1.1.dist-info/RECORD
