Metadata-Version: 2.1
Name: poetry-exp
Version: 0.1.1
Summary: test poetry ecxp
Author: Aafak Mohammad
Author-email: aafak.mitsmca09@gmail.com
Requires-Python: >=3.11,<4.0
Classifier: Programming Language :: Python :: 3
Classifier: Programming Language :: Python :: 3.11
Requires-Dist: flask (==2.3.2)
Requires-Dist: pyvmomi (==8.0.1.0.2)
